{
  "market": "futures_um",
  "interval": "1h",
  "realtime_interval": "5m",
  "realtime_limit": 1500,
  "realtime_base_url": "https://fapi.binance.com",
  "symbols": ["BTCUSDT", "ETHUSDT", "SOLUSDT", "BNBUSDT"],
  "data_base_url": "",
  "data_base_urls": [],
  "https_proxy": "",
  "auto_detect_proxy": true,
  "data_dir": "data",
  "model_dir": "models",
  "reports_dir": "reports",
  "fee_rate": 0.00045,
  "maker_fee_rate": 0.0002,
  "maker_fill_fraction": 0.0,
  "slippage_rate": 0.0002,
  "partial_fill_ratio": 1.0,
  "execution_latency_bars": 0,
  "min_order_notional_fraction": 0.0,
  "exchange_min_notional_usdt": 0.0,
  "exchange_min_quantity": 0.0,
  "exchange_max_quantity": 0.0,
  "exchange_quantity_step": 0.0,
  "exchange_price_tick_size": 0.0,
  "exchange_downtime_guard_enabled": true,
  "exchange_gap_recovery_bars": 1,
  "liquidity_execution_enabled": true,
  "max_bar_participation_rate": 0.01,
  "liquidity_lookback_bars": 48,
  "slippage_impact_coefficient": 1.0,
  "max_dynamic_slippage_rate": 0.02,
  "liquidation_guard_enabled": true,
  "maintenance_margin_rate": 0.005,
  "liquidation_buffer": 0.01,
  "liquidation_fee_rate": 0.005,
  "max_leverage": 3,
  "default_leverage": 1,
  "margin_type": "ISOLATED",
  "risk_per_trade": 0.005,
  "ewma_volatility_enabled": true,
  "ewma_volatility_span": 48,
  "ewma_daily_volatility_target": 0.03,
  "funding_crowding_guard_enabled": true,
  "funding_crowding_max_rate": 0.0005,
  "regime_risk_guard_enabled": true,
  "regime_detection_method": "rule_based",
  "regime_statistical_clusters": 4,
  "regime_statistical_min_history": 240,
  "regime_statistical_lookback": 720,
  "regime_statistical_refit_interval": 24,
  "regime_statistical_random_seed": 42,
  "max_daily_loss": 0.03,
  "long_threshold": 0.57,
  "short_threshold": 0.43,
  "min_confidence_gap": 0.07,
  "label_horizon": 3,
  "label_min_return": 0.001,
  "train_fraction": 0.7,
  "validation_fraction": 0.15,
  "random_seed": 42,
  "monitoring_recent_rows": 240,
  "monitoring_psi_threshold": 0.25,
  "monitoring_ks_threshold": 0.2,
  "monitoring_min_confidence": 0.12,
  "monitoring_max_ece": 0.15,
  "monitoring_min_rolling_sharpe": 0.0,
  "monitoring_max_drawdown": 0.08,
  "monitoring_return_deviation": 0.03,
  "monitoring_regime_shift_threshold": 0.35,
  "monitoring_trigger_max_age_hours": 6,
  "monitoring_min_consecutive_breaches": 2,
  "portfolio_target_gross_exposure": 0.45,
  "portfolio_max_total_leverage": 1.0,
  "portfolio_max_single_weight": 0.25,
  "portfolio_max_sector_exposure": 0.35,
  "portfolio_max_cluster_exposure": 0.35,
  "portfolio_min_liquidity_score": 0.2,
  "portfolio_max_drawdown": 0.1,
  "portfolio_volatility_floor": 0.001,
  "portfolio_volatility_target_enabled": true,
  "portfolio_target_daily_volatility": 0.02,
  "portfolio_min_volatility_observations": 100,
  "portfolio_correlation_threshold": 0.75,
  "portfolio_correlation_lookback": 500,
  "portfolio_cvar_confidence": 0.95,
  "portfolio_max_cvar_loss": 0.01,
  "portfolio_min_cvar_observations": 100,
  "portfolio_paper_initial_balance": 10000.0,
  "portfolio_paper_max_history": 2000,
  "portfolio_require_complete_inputs": true,
  "shadow_learning_enabled": true,
  "shadow_min_signal_count": 8,
  "shadow_min_profit_factor": 1.2,
  "shadow_max_position_fraction": 0.05,
  "shadow_leverage": 1,
  "shadow_target_gross_exposure": 0.2,
  "runner_max_model_trials": 4,
  "runner_time_budget_minutes": 6.0,
  "runner_rolling_folds": 1,
  "runner_max_training_rows": 8000,
  "portfolio_symbol_sectors": {
    "BTCUSDT": "bitcoin",
    "ETHUSDT": "layer1",
    "SOLUSDT": "layer1",
    "BNBUSDT": "exchange"
  },
  "live_trading_enabled": false
}
